movie_nfo_generator/__init__.py
movie_nfo_generator/__main__.py
movie_nfo_generator/config.py
movie_nfo_generator/nfo.py
movie_nfo_generator/scraper_tmdb.py
movie_nfo_generator/utilities.py
movie_nfo_generator-1.0.2.dist-info/LICENSE
movie_nfo_generator-1.0.2.dist-info/METADATA
movie_nfo_generator-1.0.2.dist-info/WHEEL
movie_nfo_generator-1.0.2.dist-info/entry_points.txt
movie_nfo_generator-1.0.2.dist-info/top_level.txt
movie_nfo_generator-1.0.2.dist-info/zip-safe
movie_nfo_generator-1.0.2.dist-info/RECORD
