Metadata-Version: 2.1
Name: movie-nfo-generator
Version: 1.0.2
Summary: A simple tool to generate NFO files for Kodi.
Home-page: https://github.com/JGoutin/movie_nfo_generator
Author: J.Goutin
License: GPLv3
Project-URL: Download, https://pypi.org/project/movie_nfo_generator
Keywords: kodi nfo
Platform: UNKNOWN
Classifier: Development Status :: 5 - Production/Stable
Classifier: Environment :: Console
Classifier: Intended Audience :: End Users/Desktop
Classifier: License :: OSI Approved :: GNU General Public License v3 (GPLv3)
Classifier: Programming Language :: Python
Classifier: Programming Language :: Python :: 3
Classifier: Programming Language :: Python :: 3.6
Classifier: Programming Language :: Python :: 3.7
Classifier: Programming Language :: Python :: 3.8
Classifier: Programming Language :: Python :: 3.9
Classifier: Programming Language :: Python :: 3.10
Classifier: Topic :: Multimedia
Requires-Python: >=3.6
License-File: LICENSE
Requires-Dist: lxml
Requires-Dist: tmdbsimple
Requires-Dist: requests
